pydistmaker/__init__.py
pydistmaker/__main__.py
pydistmaker/cli.py
pydistmaker/config.py
pydistmaker/packager.py
pydistmaker/schema.py
pydistmaker-0.1.0.dist-info/entry_points.txt
pydistmaker-0.1.0.dist-info/LICENSE
pydistmaker-0.1.0.dist-info/METADATA
pydistmaker-0.1.0.dist-info/WHEEL
pydistmaker-0.1.0.dist-info/RECORD
