Metadata-Version: 2.1
Name: pydistmaker
Version: 0.1.0
Summary: 
Author: yang, qingfeng
Author-email: 319511269@qq.com
Requires-Python: >=3.11,<3.14
Classifier: Programming Language :: Python :: 3
Classifier: Programming Language :: Python :: 3.11
Classifier: Programming Language :: Python :: 3.12
Classifier: Programming Language :: Python :: 3.13
Requires-Dist: click (>=8.1.8,<9.0.0)
Requires-Dist: jsonschema (>=4.23.0,<5.0.0)
Requires-Dist: nuitka (>=2.6.8,<3.0.0)
Requires-Dist: pydantic (>=2.10.6,<3.0.0)
Requires-Dist: pyinstaller (>=6.12.0,<7.0.0)
